repo_to_llm/__init__.py
repo_to_llm/cli.py
repo_to_llm/config.py
repo_to_llm/core.py
repo_to_llm/pattern_matching.py
repo_to_llm/utils.py
repo_to_llm-0.1.1.dist-info/licenses/LICENSE
repo_to_llm-0.1.1.dist-info/METADATA
repo_to_llm-0.1.1.dist-info/WHEEL
repo_to_llm-0.1.1.dist-info/entry_points.txt
repo_to_llm-0.1.1.dist-info/top_level.txt
repo_to_llm-0.1.1.dist-info/RECORD
