Metadata-Version: 2.4
Name: repo-to-llm
Version: 0.1.1
Summary: CLI tool to convert a code repository into LLM-friendly markdown
Author-email: Luca Bottero <lucabottero99@gmail.com>
License: MIT License
Project-URL: Homepage, https://github.com/luca-bottero/repo-to-llm
Project-URL: Repository, https://github.com/luca-bottero/repo-to-llm
Project-URL: Bug Tracker, https://github.com/luca-bottero/repo-to-llm/issues
Keywords: cli,llm,markdown,codebase,repo,repository
Classifier: Programming Language :: Python :: 3
Classifier: License :: OSI Approved :: MIT License
Classifier: Operating System :: OS Independent
Classifier: Topic :: Software Development :: Libraries :: Python Modules
Requires-Python: >=3.8
License-File: LICENSE
Requires-Dist: gitignore-parser
Dynamic: license-file
